{"cameraMode":{"drawMode":0,"name":"Shaded","section":"Shading Mode"},"sceneLighting":false,"audioPlay":false,"sceneViewState":{"m_AlwaysRefresh":false,"showFog":true,"showSkybox":false,"showFlares":true,"showImageEffects":true,"showParticleSystems":true,"showVisualEffectGraphs":true,"m_FxEnabled":false},"in2DMode":false,"pivot":{"x":405.5,"y":286.67999267578127,"z":0.0},"rotation":{"x":-0.26702985167503359,"y":-0.0008697669254615903,"z":0.00024098735593724996,"w":-0.9636885523796082},"size":281.5689697265625,"orthographic":false}